geolocation_fields/__init__.py
geolocation_fields/apps.py
geolocation_fields/settings.py
geolocation_fields/tests.py
geolocation_fields/views.py
geolocation_fields/__pycache__/__init__.cpython-36.pyc
geolocation_fields/forms/__init__.py
geolocation_fields/forms/fields.py
geolocation_fields/forms/widgets.py
geolocation_fields/migrations/__init__.py
geolocation_fields/models/__init__.py
geolocation_fields/models/base.py
geolocation_fields/models/fields.py
geolocation_fields/models/values_checks.py
geolocation_fields/models/__pycache__/__init__.cpython-36.pyc
geolocation_fields/models/__pycache__/base.cpython-36.pyc
geolocation_fields/static/leaflet/leaflet-src.esm.js
geolocation_fields/static/leaflet/leaflet-src.esm.js.map
geolocation_fields/static/leaflet/leaflet-src.js
geolocation_fields/static/leaflet/leaflet-src.js.map
geolocation_fields/static/leaflet/leaflet.css
geolocation_fields/static/leaflet/leaflet.js
geolocation_fields/static/leaflet/leaflet.js.map
geolocation_fields/static/leaflet/images/layers-2x.png
geolocation_fields/static/leaflet/images/layers.png
geolocation_fields/static/leaflet/images/marker-icon-2x.png
geolocation_fields/static/leaflet/images/marker-icon.png
geolocation_fields/static/leaflet/images/marker-shadow.png
geolocation_fields/static/polygon/icons8-polygon-24.png
geolocation_fields/static/polygon/icons8-polygon-48.png
geolocation_fields/static/polygon/icons8-polygon-96.png
geolocation_fields/static/vendor/jquery-2.2.4.min.js
geolocation_fields/static/widgets/css/point.css
geolocation_fields/static/widgets/leaflet_implementations/point.js
geolocation_fields/static/widgets/leaflet_implementations/polygon.js
geolocation_fields/static/widgets/mapbox_implementations/point.js
geolocation_fields/templates/widgets/point.html
geolocation_fields/templates/widgets/polygon.html
geolocation_fields/templates/widgets/map_control/control.html
django_geolocation_fields-0.1.8.dist-info/AUTHORS
django_geolocation_fields-0.1.8.dist-info/LICENSE
django_geolocation_fields-0.1.8.dist-info/METADATA
django_geolocation_fields-0.1.8.dist-info/WHEEL
django_geolocation_fields-0.1.8.dist-info/top_level.txt
django_geolocation_fields-0.1.8.dist-info/RECORD
